CMakeLists.txt
MANIFEST.in
README.md
VERSION
setup.cfg
setup.py
arbor/CMakeLists.txt
arbor/algorithms.hpp
arbor/arbexcept.cpp
arbor/assert.cpp
arbor/benchmark_cell_group.cpp
arbor/benchmark_cell_group.hpp
arbor/builtin_mechanisms.cpp
arbor/builtin_mechanisms.hpp
arbor/cable_cell.cpp
arbor/cable_cell_param.cpp
arbor/cell_group.hpp
arbor/cell_group_factory.cpp
arbor/cell_group_factory.hpp
arbor/common_types_io.cpp
arbor/connection.hpp
arbor/cv_policy.cpp
arbor/distributed_context.hpp
arbor/epoch.hpp
arbor/event_binner.cpp
arbor/event_binner.hpp
arbor/event_queue.hpp
arbor/execution_context.cpp
arbor/execution_context.hpp
arbor/fvm_layout.cpp
arbor/fvm_layout.hpp
arbor/fvm_lowered_cell.hpp
arbor/fvm_lowered_cell_impl.cpp
arbor/fvm_lowered_cell_impl.hpp
arbor/gpu_context.cpp
arbor/gpu_context.hpp
arbor/lif_cell_group.cpp
arbor/lif_cell_group.hpp
arbor/matrix.hpp
arbor/mc_cell_group.cpp
arbor/mc_cell_group.hpp
arbor/mechcat.cpp
arbor/merge_events.cpp
arbor/merge_events.hpp
arbor/partition_load_balance.cpp
arbor/s_expr.cpp
arbor/s_expr.hpp
arbor/sampler_map.hpp
arbor/schedule.cpp
arbor/simulation.cpp
arbor/spike_event_io.cpp
arbor/spike_source_cell_group.cpp
arbor/spike_source_cell_group.hpp
arbor/symmetric_recipe.cpp
arbor/thread_private_spike_store.cpp
arbor/thread_private_spike_store.hpp
arbor/tree.cpp
arbor/tree.hpp
arbor/version.cpp
arbor/backends/builtin_mech_proto.hpp
arbor/backends/event.hpp
arbor/backends/event_delivery.md
arbor/backends/matrix_storage.md
arbor/backends/multi_event_stream_state.hpp
arbor/backends/threshold_crossing.hpp
arbor/backends/gpu/cuda_api.hpp
arbor/backends/gpu/forest.cpp
arbor/backends/gpu/forest.hpp
arbor/backends/gpu/fvm.cpp
arbor/backends/gpu/fvm.hpp
arbor/backends/gpu/gpu_api.hpp
arbor/backends/gpu/gpu_common.hpp
arbor/backends/gpu/gpu_store_types.hpp
arbor/backends/gpu/hip_api.hpp
arbor/backends/gpu/math_cu.hpp
arbor/backends/gpu/matrix_assemble.cu
arbor/backends/gpu/matrix_common.hpp
arbor/backends/gpu/matrix_fine.cu
arbor_bcumming.egg-info/PKG-INFO
arbor_bcumming.egg-info/SOURCES.txt
arbor_bcumming.egg-info/dependency_links.txt
arbor_bcumming.egg-info/not-zip-safe
arbor_bcumming.egg-info/requires.txt
arbor_bcumming.egg-info/top_level.txt
