Metadata-Version: 2.1
Name: arbor-bcumming
Version: 0.5
Summary: High performance simulation of networks of multicompartment neurons.
Home-page: https://github.com/arbor-sim/arbor
Author: The Arbor dev team.
License: UNKNOWN
Project-URL: Source, https://github.com/arbor-sim/arbor
Project-URL: Documentation, https://arbor.readthedocs.io
Project-URL: Bug Reports, https://github.com/arbor-sim/arbor/issues
Platform: UNKNOWN
Classifier: Development Status :: 5 - Production/Stable
Classifier: Intended Audience :: Science/Research
Classifier: License :: OSI Approved :: BSD License
Classifier: Programming Language :: Python :: 3.6
Classifier: Programming Language :: Python :: 3.7
Classifier: Programming Language :: Python :: 3.8
Classifier: Programming Language :: C++
Requires-Python: >=3.6
